odoo/addons/industry_fsm_sale_default_task/LICENSE
odoo/addons/industry_fsm_sale_default_task/README.rst
odoo/addons/industry_fsm_sale_default_task/__init__.py
odoo/addons/industry_fsm_sale_default_task/__manifest__.py
odoo/addons/industry_fsm_sale_default_task/images/screen.png
odoo/addons/industry_fsm_sale_default_task/models/__init__.py
odoo/addons/industry_fsm_sale_default_task/models/sale_order.py
odoo/addons/industry_fsm_sale_default_task/static/description/icon.png
odoo/addons/industry_fsm_sale_default_task/static/description/index.html
odoo_addon_industry_fsm_sale_default_task-16.0.1.1.0.dist-info/METADATA
odoo_addon_industry_fsm_sale_default_task-16.0.1.1.0.dist-info/WHEEL
odoo_addon_industry_fsm_sale_default_task-16.0.1.1.0.dist-info/top_level.txt
odoo_addon_industry_fsm_sale_default_task-16.0.1.1.0.dist-info/RECORD
