Metadata-Version: 2.1
Name: odoo-addon-industry_fsm_sale_default_task
Version: 16.0.1.1.0
Requires-Python: >=3.10
Requires-Dist: odoo>=16.0a,<16.1dev
Summary: Additional sale order lines will be linked with field service project task.
Home-page: https://www.mint-system.ch/
License: OPL-1
Author: Mint System GmbH
Classifier: Programming Language :: Python
Classifier: Framework :: Odoo
Classifier: Framework :: Odoo :: 16.0
